stowrap/__init__.py
stowrap/client.py
stowrap-0.0.1.dist-info/LICENSE
stowrap-0.0.1.dist-info/METADATA
stowrap-0.0.1.dist-info/WHEEL
stowrap-0.0.1.dist-info/top_level.txt
stowrap-0.0.1.dist-info/RECORD
